{"resources": {"1": {"ri": "id-in", "rn": "cse-in", "csi": "/id-in", "rr": true, "csz": ["application/json", "application/cbor"], "acpi": ["/id-in/acpCreateACPs"], "poa": ["http://127.0.0.1:8080"], "__imported__": true, "pi": "", "ct": "20230418T131530,467158", "lt": "20230418T131530,467158", "ty": 5, "__rtype__": "m2m:cb", "__announcedTo__": [], "srt": [1, 2, 3, 4, 5, 9, 13, 14, 15, 16, 17, 23, 24, 28, 29, 30, 48, 58, 60, 63, 10001, 10002, 10003, 10004, 10009, 10013, 10014, 10016, 10024, 10028, 10029, 10030, 10060, 10063], "srv": ["2a", "3", "4"], "cst": 1, "__srn__": "cse-in", "__originator__": "CAdmin"}, "2": {"rn": "acpCreateACPs", "ri": "acpCreateACPs", "pi": "id-in", "pv": {"acr": [{"acor": ["all"], "acod": [{"chty": [1]}], "acop": 1}]}, "pvs": {"acr": [{"acor": ["CAdmin"], "acop": 63}]}, "__imported__": true, "ct": "20230418T131530,477008", "lt": "20230418T131530,477008", "et": "20280416T131530,477020", "ty": 1, "__rtype__": "m2m:acp", "__announcedTo__": [], "__srn__": "cse-in/acpCreateACPs", "__originator__": "CAdmin"}, "3": {"ri": "CAdmin", "rn": "CAdmin", "pi": "id-in", "rr": true, "api": "NCAdmin", "aei": "CAdmin", "csz": ["application/json", "application/cbor"], "__imported__": true, "ct": "20230418T131530,493730", "lt": "20230418T131530,493730", "et": "20280416T131530,493743", "ty": 2, "__rtype__": "m2m:ae", "__announcedTo__": [], "__srn__": "cse-in/CAdmin", "__originator__": "CAdmin"}, "4": {"api": "N.smartswitch", "poa": ["http://192.168.1.2:8080/smartswitch"], "rn": "smartswitch", "srv": ["3"], "rr": false, "ri": "CmqWvsV0Tlo", "pi": "id-in", "ct": "20230509T110331,116957", "lt": "20230509T110331,116957", "et": "20280507T110331,116957", "ty": 2, "__rtype__": "m2m:ae", "__announcedTo__": [], "aei": "CmqWvsV0Tlo", "__srn__": "cse-in/smartswitch", "__rvi__": "3", "__originator__": "CmqWvsV0Tlo"}, "5": {"api": "N.lightbulb1", "poa": ["http://192.168.1.3:8080/lightbulb1"], "rn": "lightbulb1", "srv": ["3"], "rr": false, "ri": "Chn8GEr0y0t", "pi": "id-in", "ct": "20230509T110333,194411", "lt": "20230509T110333,194411", "et": "20280507T110333,194411", "ty": 2, "__rtype__": "m2m:ae", "__announcedTo__": [], "aei": "Chn8GEr0y0t", "__srn__": "cse-in/lightbulb1", "__rvi__": "3", "__originator__": "Chn8GEr0y0t"}, "6": {"api": "N.lightbulb2", "poa": ["http://192.168.1.4:8080/lightbulb2"], "rn": "lightbulb2", "srv": ["3"], "rr": false, "ri": "CibfhRe65ER", "pi": "id-in", "ct": "20230509T110335,249677", "lt": "20230509T110335,249677", "et": "20280507T110335,249677", "ty": 2, "__rtype__": "m2m:ae", "__announcedTo__": [], "aei": "CibfhRe65ER", "__srn__": "cse-in/lightbulb2", "__rvi__": "3", "__originator__": "CibfhRe65ER"}, "7": {"mbs": 10000, "mni": 10, "rn": "state", "ri": "cnt1144691727681054454", "pi": "CmqWvsV0Tlo", "ct": "20230509T110337,318505", "lt": "20230509T110337,318505", "et": "20280507T110337,318505", "ty": 3, "__rtype__": "m2m:cnt", "__announcedTo__": [], "cni": 1, "cbs": 33, "st": 1, "__srn__": "cse-in/smartswitch/state", "__rvi__": "3", "__originator__": "CAdmin"}, "8": {"ri": "la7727977178357297274", "pi": "cnt1144691727681054454", "rn": "la", "__srn__": "cse-in/smartswitch/state/la", "ct": "20230509T110337,351056", "lt": "20230509T110337,351056", "et": "20280507T110337,351056", "ty": 20002, "__rtype__": "m2m:la", "__announcedTo__": []}, "9": {"ri": "ol2952826138008939109", "pi": "cnt1144691727681054454", "rn": "ol", "__srn__": "cse-in/smartswitch/state/ol", "ct": "20230509T110337,362077", "lt": "20230509T110337,362077", "et": "20280507T110337,362077", "ty": 20001, "__rtype__": "m2m:ol", "__announcedTo__": []}, "10": {"mbs": 10000, "mni": 10, "rn": "state", "ri": "cnt933344632986570619", "pi": "Chn8GEr0y0t", "ct": "20230509T110339,421396", "lt": "20230509T110339,421396", "et": "20280507T110339,421396", "ty": 3, "__rtype__": "m2m:cnt", "__announcedTo__": [], "cni": 1, "cbs": 16, "st": 1, "__srn__": "cse-in/lightbulb1/state", "__rvi__": "3", "__originator__": "CAdmin"}, "11": {"ri": "la8739079743636998475", "pi": "cnt933344632986570619", "rn": "la", "__srn__": "cse-in/lightbulb1/state/la", "ct": "20230509T110339,446170", "lt": "20230509T110339,446170", "et": "20280507T110339,446170", "ty": 20002, "__rtype__": "m2m:la", "__announcedTo__": []}, "12": {"ri": "ol8017183053995090508", "pi": "cnt933344632986570619", "rn": "ol", "__srn__": "cse-in/lightbulb1/state/ol", "ct": "20230509T110339,467681", "lt": "20230509T110339,467681", "et": "20280507T110339,467681", "ty": 20001, "__rtype__": "m2m:ol", "__announcedTo__": []}, "13": {"mbs": 10000, "mni": 10, "rn": "state", "ri": "cnt3332947889552595692", "pi": "CibfhRe65ER", "ct": "20230509T110341,509530", "lt": "20230509T110341,509530", "et": "20280507T110341,509530", "ty": 3, "__rtype__": "m2m:cnt", "__announcedTo__": [], "cni": 0, "cbs": 0, "st": 0, "__srn__": "cse-in/lightbulb2/state", "__rvi__": "3", "__originator__": "CAdmin"}, "14": {"ri": "la6091203060936724701", "pi": "cnt3332947889552595692", "rn": "la", "__srn__": "cse-in/lightbulb2/state/la", "ct": "20230509T110341,522530", "lt": "20230509T110341,522530", "et": "20280507T110341,522530", "ty": 20002, "__rtype__": "m2m:la", "__announcedTo__": []}, "15": {"ri": "ol7725054297437411439", "pi": "cnt3332947889552595692", "rn": "ol", "__srn__": "cse-in/lightbulb2/state/ol", "ct": "20230509T110341,531530", "lt": "20230509T110341,531530", "et": "20280507T110341,531530", "ty": 20001, "__rtype__": "m2m:ol", "__announcedTo__": []}, "16": {"cnf": "text/plain:0", "con": "{\"controlledLight\": \"lightbulb1\"}", "rn": "smartswitch-instance_0", "ri": "cin6175092804710247549", "pi": "cnt1144691727681054454", "ct": "20230509T110343,570427", "lt": "20230509T110343,570427", "et": "20280507T110343,570427", "ty": 4, "__rtype__": "m2m:cin", "__announcedTo__": [], "cs": 33, "st": 1, "__srn__": "cse-in/smartswitch/state/smartswitch-instance_0", "__rvi__": "3", "__originator__": "CAdmin"}, "17": {"cnf": "text/plain:0", "con": "{\"state\": \"off\"}", "rn": "lightbulb1-instance_0", "ri": "cin5799542867258629421", "pi": "cnt933344632986570619", "ct": "20230509T110345,658563", "lt": "20230509T110345,658563", "et": "20280507T110345,658563", "ty": 4, "__rtype__": "m2m:cin", "__announcedTo__": [], "cs": 16, "st": 1, "__srn__": "cse-in/lightbulb1/state/lightbulb1-instance_0", "__rvi__": "3", "__originator__": "CAdmin"}}}